{
    "datestamp": "21-Mar-2024",
    "SRING-Italia": [
        {
            "name": "Ducato di Milano",
            "population": 451
        },
        {
            "name": "Ducato di Modena",
            "population": 477
        },
        {
            "name": "Repubblica di Genova",
            "population": 405
        },
        {
            "name": "Repubblica fiorentina",
            "population": 611
        },
        {
            "name": "Repubblica di Siena",
            "population": 178
        }
    ],
    "Regno Delle Due Sicilie": [
        {
            "name": "Provincia di Terra di Lavoro",
            "population": 316
        },
        {
            "name": "Provincia degli Abruzzi",
            "population": 335
        }
    ],
    "Serenissima Repubblica di Venezia": [
        {
            "name": "Serenissima Repubblica di Venezia",
            "population": 249
        }
    ]
}